[
  {
    "id": 999999,
    "level_id": 999999,
    "block_id": 1,
    "cost": [
      {
        "x": 1,
        "y": 0,
        "z": 5
      }
    ],
    "money": 500,
    "exp": 220,
    "patrol_unit": 10001,
    "patrol_once": [
      {
        "x": 5,
        "y": 1020000,
        "z": 5
      },
      {
        "x": 5,
        "y": 5012001,
        "z": 1
      },
      {
        "x": 5,
        "y": 1030002,
        "z": 0
      }
    ],
    "sweep_once": [
      {
        "x": 4,
        "y": 0,
        "z": 2000
      },
      {
        "x": 3,
        "y": 0,
        "z": 5000
      },
      {
        "x": 5,
        "y": 5012001,
        "z": 3
      }
    ],
    "sweep_monster_once": [
      {
        "x": 500,
        "y": 3,
        "z": 5
      }
    ]
  },
  {
    "id": 1,
    "level_id": 10001,
    "block_id": 1,
    "cost": [
      {
        "x": 1,
        "y": 0,
        "z": 5
      }
    ],
    "money": 500,
    "exp": 220,
    "patrol_unit": 10001,
    "patrol_once": [
      {
        "x": 5,
        "y": 1020000,
        "z": 5
      },
      {
        "x": 5,
        "y": 5012001,
        "z": 1
      },
      {
        "x": 5,
        "y": 1030002,
        "z": 0
      }
    ],
    "sweep_once": [
      {
        "x": 4,
        "y": 0,
        "z": 2000
      },
      {
        "x": 3,
        "y": 0,
        "z": 5000
      },
      {
        "x": 5,
        "y": 5012001,
        "z": 3
      }
    ],
    "sweep_monster_once": [
      {
        "x": 500,
        "y": 3,
        "z": 5
      }
    ]
  },
  {
    "id": 2,
    "level_id": 10002,
    "block_id": 1,
    "cost": [
      {
        "x": 1,
        "y": 0,
        "z": 5
      }
    ],
    "money": 550,
    "exp": 240,
    "patrol_unit": 10002,
    "patrol_once": [
      {
        "x": 5,
        "y": 1020000,
        "z": 5
      },
      {
        "x": 5,
        "y": 5012001,
        "z": 1
      },
      {
        "x": 5,
        "y": 1030002,
        "z": 0
      }
    ],
    "sweep_once": [
      {
        "x": 4,
        "y": 0,
        "z": 2000
      },
      {
        "x": 3,
        "y": 0,
        "z": 5000
      },
      {
        "x": 5,
        "y": 5012001,
        "z": 3
      }
    ],
    "sweep_monster_once": [
      {
        "x": 500,
        "y": 3,
        "z": 5
      }
    ]
  },
  {
    "id": 3,
    "level_id": 10003,
    "block_id": 1,
    "cost": [
      {
        "x": 1,
        "y": 0,
        "z": 5
      }
    ],
    "money": 650,
    "exp": 260,
    "patrol_unit": 10003,
    "patrol_once": [
      {
        "x": 5,
        "y": 1020000,
        "z": 5
      },
      {
        "x": 5,
        "y": 5012001,
        "z": 1
      },
      {
        "x": 5,
        "y": 1030002,
        "z": 0
      }
    ],
    "sweep_once": [
      {
        "x": 4,
        "y": 0,
        "z": 2000
      },
      {
        "x": 3,
        "y": 0,
        "z": 5000
      },
      {
        "x": 5,
        "y": 5012001,
        "z": 3
      }
    ],
    "sweep_monster_once": [
      {
        "x": 500,
        "y": 3,
        "z": 5
      }
    ]
  },
  {
    "id": 4,
    "level_id": 10004,
    "block_id": 1,
    "cost": [
      {
        "x": 1,
        "y": 0,
        "z": 5
      }
    ],
    "money": 700,
    "exp": 280,
    "patrol_unit": 10004,
    "patrol_once": [
      {
        "x": 5,
        "y": 1020000,
        "z": 5
      },
      {
        "x": 5,
        "y": 5012001,
        "z": 1
      },
      {
        "x": 5,
        "y": 1030002,
        "z": 0
      }
    ],
    "sweep_once": [
      {
        "x": 4,
        "y": 0,
        "z": 2000
      },
      {
        "x": 3,
        "y": 0,
        "z": 5000
      },
      {
        "x": 5,
        "y": 5012001,
        "z": 3
      }
    ],
    "sweep_monster_once": [
      {
        "x": 500,
        "y": 3,
        "z": 5
      }
    ]
  },
  {
    "id": 5,
    "level_id": 10005,
    "block_id": 1,
    "cost": [
      {
        "x": 1,
        "y": 0,
        "z": 5
      }
    ],
    "money": 750,
    "exp": 300,
    "patrol_unit": 10005,
    "patrol_once": [
      {
        "x": 5,
        "y": 1020000,
        "z": 6
      },
      {
        "x": 5,
        "y": 5012001,
        "z": 1
      },
      {
        "x": 5,
        "y": 1030002,
        "z": 0
      }
    ],
    "sweep_once": [
      {
        "x": 4,
        "y": 0,
        "z": 2000
      },
      {
        "x": 3,
        "y": 0,
        "z": 5000
      },
      {
        "x": 5,
        "y": 5012001,
        "z": 3
      }
    ],
    "sweep_monster_once": [
      {
        "x": 500,
        "y": 3,
        "z": 5
      }
    ]
  },
  {
    "id": 6,
    "level_id": 10006,
    "block_id": 1,
    "cost": [
      {
        "x": 1,
        "y": 0,
        "z": 5
      }
    ],
    "money": 800,
    "exp": 320,
    "patrol_unit": 10006,
    "patrol_once": [
      {
        "x": 5,
        "y": 1020000,
        "z": 6
      },
      {
        "x": 5,
        "y": 5012001,
        "z": 1
      },
      {
        "x": 5,
        "y": 1030002,
        "z": 0
      }
    ],
    "sweep_once": [
      {
        "x": 4,
        "y": 0,
        "z": 2000
      },
      {
        "x": 3,
        "y": 0,
        "z": 5000
      },
      {
        "x": 5,
        "y": 5012001,
        "z": 3
      }
    ],
    "sweep_monster_once": [
      {
        "x": 500,
        "y": 3,
        "z": 5
      }
    ]
  },
  {
    "id": 7,
    "level_id": 10007,
    "block_id": 1,
    "cost": [
      {
        "x": 1,
        "y": 0,
        "z": 5
      }
    ],
    "money": 850,
    "exp": 340,
    "patrol_unit": 10007,
    "patrol_once": [
      {
        "x": 5,
        "y": 1020000,
        "z": 7
      },
      {
        "x": 5,
        "y": 5012001,
        "z": 1
      },
      {
        "x": 5,
        "y": 1030002,
        "z": 0
      }
    ],
    "sweep_once": [
      {
        "x": 4,
        "y": 0,
        "z": 2000
      },
      {
        "x": 3,
        "y": 0,
        "z": 5000
      },
      {
        "x": 5,
        "y": 5012001,
        "z": 3
      }
    ],
    "sweep_monster_once": [
      {
        "x": 500,
        "y": 3,
        "z": 5
      }
    ]
  },
  {
    "id": 8,
    "level_id": 10008,
    "block_id": 1,
    "cost": [
      {
        "x": 1,
        "y": 0,
        "z": 5
      }
    ],
    "money": 900,
    "exp": 360,
    "patrol_unit": 10008,
    "patrol_once": [
      {
        "x": 5,
        "y": 1020000,
        "z": 7
      },
      {
        "x": 5,
        "y": 5012001,
        "z": 1
      },
      {
        "x": 5,
        "y": 1030002,
        "z": 50
      }
    ],
    "sweep_once": [
      {
        "x": 4,
        "y": 0,
        "z": 2000
      },
      {
        "x": 3,
        "y": 0,
        "z": 5000
      },
      {
        "x": 5,
        "y": 5012001,
        "z": 3
      }
    ],
    "sweep_monster_once": [
      {
        "x": 500,
        "y": 3,
        "z": 5
      }
    ]
  },
  {
    "id": 9,
    "level_id": 10009,
    "block_id": 1,
    "cost": [
      {
        "x": 1,
        "y": 0,
        "z": 5
      }
    ],
    "money": 950,
    "exp": 380,
    "patrol_unit": 10009,
    "patrol_once": [
      {
        "x": 5,
        "y": 1020000,
        "z": 7
      },
      {
        "x": 5,
        "y": 5012001,
        "z": 1
      },
      {
        "x": 5,
        "y": 1030002,
        "z": 50
      }
    ],
    "sweep_once": [
      {
        "x": 4,
        "y": 0,
        "z": 2000
      },
      {
        "x": 3,
        "y": 0,
        "z": 5000
      },
      {
        "x": 5,
        "y": 5012001,
        "z": 3
      }
    ],
    "sweep_monster_once": [
      {
        "x": 500,
        "y": 3,
        "z": 5
      }
    ]
  },
  {
    "id": 10,
    "level_id": 10010,
    "block_id": 1,
    "cost": [
      {
        "x": 1,
        "y": 0,
        "z": 5
      }
    ],
    "money": 1000,
    "exp": 400,
    "patrol_unit": 10010,
    "patrol_once": [
      {
        "x": 5,
        "y": 1020000,
        "z": 8
      },
      {
        "x": 5,
        "y": 5012001,
        "z": 1
      },
      {
        "x": 5,
        "y": 1030002,
        "z": 50
      }
    ],
    "sweep_once": [
      {
        "x": 4,
        "y": 0,
        "z": 2000
      },
      {
        "x": 3,
        "y": 0,
        "z": 5000
      },
      {
        "x": 5,
        "y": 5012001,
        "z": 3
      }
    ],
    "sweep_monster_once": [
      {
        "x": 500,
        "y": 3,
        "z": 5
      }
    ]
  },
  {
    "id": 11,
    "level_id": 10011,
    "block_id": 2,
    "cost": [
      {
        "x": 1,
        "y": 0,
        "z": 5
      }
    ],
    "money": 1050,
    "exp": 420,
    "patrol_unit": 10011,
    "patrol_once": [
      {
        "x": 5,
        "y": 1020000,
        "z": 8
      },
      {
        "x": 5,
        "y": 5012001,
        "z": 1
      },
      {
        "x": 5,
        "y": 1030002,
        "z": 51
      }
    ],
    "sweep_once": [
      {
        "x": 4,
        "y": 0,
        "z": 2000
      },
      {
        "x": 3,
        "y": 0,
        "z": 5000
      },
      {
        "x": 5,
        "y": 5012001,
        "z": 3
      }
    ],
    "sweep_monster_once": [
      {
        "x": 500,
        "y": 3,
        "z": 5
      }
    ]
  },
  {
    "id": 12,
    "level_id": 10012,
    "block_id": 2,
    "cost": [
      {
        "x": 1,
        "y": 0,
        "z": 5
      }
    ],
    "money": 1100,
    "exp": 440,
    "patrol_unit": 10012,
    "patrol_once": [
      {
        "x": 5,
        "y": 1020000,
        "z": 8
      },
      {
        "x": 5,
        "y": 5012001,
        "z": 2
      },
      {
        "x": 5,
        "y": 1030002,
        "z": 52
      }
    ],
    "sweep_once": [
      {
        "x": 4,
        "y": 0,
        "z": 2000
      },
      {
        "x": 3,
        "y": 0,
        "z": 5000
      },
      {
        "x": 5,
        "y": 5012001,
        "z": 3
      }
    ],
    "sweep_monster_once": [
      {
        "x": 500,
        "y": 3,
        "z": 5
      }
    ]
  },
  {
    "id": 13,
    "level_id": 10013,
    "block_id": 2,
    "cost": [
      {
        "x": 1,
        "y": 0,
        "z": 5
      }
    ],
    "money": 1150,
    "exp": 460,
    "patrol_unit": 10013,
    "patrol_once": [
      {
        "x": 5,
        "y": 1020000,
        "z": 9
      },
      {
        "x": 5,
        "y": 5012001,
        "z": 2
      },
      {
        "x": 5,
        "y": 1030002,
        "z": 53
      }
    ],
    "sweep_once": [
      {
        "x": 4,
        "y": 0,
        "z": 2000
      },
      {
        "x": 3,
        "y": 0,
        "z": 5000
      },
      {
        "x": 5,
        "y": 5012001,
        "z": 3
      }
    ],
    "sweep_monster_once": [
      {
        "x": 500,
        "y": 3,
        "z": 5
      }
    ]
  },
  {
    "id": 14,
    "level_id": 10014,
    "block_id": 2,
    "cost": [
      {
        "x": 1,
        "y": 0,
        "z": 5
      }
    ],
    "money": 1200,
    "exp": 480,
    "patrol_unit": 10014,
    "patrol_once": [
      {
        "x": 5,
        "y": 1020000,
        "z": 9
      },
      {
        "x": 5,
        "y": 5012001,
        "z": 2
      },
      {
        "x": 5,
        "y": 1030002,
        "z": 54
      }
    ],
    "sweep_once": [
      {
        "x": 4,
        "y": 0,
        "z": 2000
      },
      {
        "x": 3,
        "y": 0,
        "z": 5000
      },
      {
        "x": 5,
        "y": 5012001,
        "z": 3
      }
    ],
    "sweep_monster_once": [
      {
        "x": 500,
        "y": 3,
        "z": 5
      }
    ]
  },
  {
    "id": 15,
    "level_id": 10015,
    "block_id": 2,
    "cost": [
      {
        "x": 1,
        "y": 0,
        "z": 5
      }
    ],
    "money": 1250,
    "exp": 500,
    "patrol_unit": 10015,
    "patrol_once": [
      {
        "x": 5,
        "y": 1020000,
        "z": 9
      },
      {
        "x": 5,
        "y": 5012001,
        "z": 2
      },
      {
        "x": 5,
        "y": 1030002,
        "z": 55
      }
    ],
    "sweep_once": [
      {
        "x": 4,
        "y": 0,
        "z": 2000
      },
      {
        "x": 3,
        "y": 0,
        "z": 5000
      },
      {
        "x": 5,
        "y": 5012001,
        "z": 3
      }
    ],
    "sweep_monster_once": [
      {
        "x": 500,
        "y": 3,
        "z": 5
      }
    ]
  },
  {
    "id": 16,
    "level_id": 10016,
    "block_id": 2,
    "cost": [
      {
        "x": 1,
        "y": 0,
        "z": 5
      }
    ],
    "money": 1300,
    "exp": 520,
    "patrol_unit": 10016,
    "patrol_once": [
      {
        "x": 5,
        "y": 1020000,
        "z": 9
      },
      {
        "x": 5,
        "y": 5012001,
        "z": 2
      },
      {
        "x": 5,
        "y": 1030002,
        "z": 56
      }
    ],
    "sweep_once": [
      {
        "x": 4,
        "y": 0,
        "z": 2000
      },
      {
        "x": 3,
        "y": 0,
        "z": 5000
      },
      {
        "x": 5,
        "y": 5012001,
        "z": 3
      }
    ],
    "sweep_monster_once": [
      {
        "x": 500,
        "y": 3,
        "z": 5
      }
    ]
  },
  {
    "id": 17,
    "level_id": 10017,
    "block_id": 2,
    "cost": [
      {
        "x": 1,
        "y": 0,
        "z": 5
      }
    ],
    "money": 1350,
    "exp": 540,
    "patrol_unit": 10017,
    "patrol_once": [
      {
        "x": 5,
        "y": 1020000,
        "z": 10
      },
      {
        "x": 5,
        "y": 5012001,
        "z": 2
      },
      {
        "x": 5,
        "y": 1030002,
        "z": 57
      }
    ],
    "sweep_once": [
      {
        "x": 4,
        "y": 0,
        "z": 2000
      },
      {
        "x": 3,
        "y": 0,
        "z": 5000
      },
      {
        "x": 5,
        "y": 5012001,
        "z": 3
      }
    ],
    "sweep_monster_once": [
      {
        "x": 500,
        "y": 3,
        "z": 5
      }
    ]
  },
  {
    "id": 18,
    "level_id": 10018,
    "block_id": 2,
    "cost": [
      {
        "x": 1,
        "y": 0,
        "z": 5
      }
    ],
    "money": 1400,
    "exp": 560,
    "patrol_unit": 10018,
    "patrol_once": [
      {
        "x": 5,
        "y": 1020000,
        "z": 10
      },
      {
        "x": 5,
        "y": 5012001,
        "z": 2
      },
      {
        "x": 5,
        "y": 1030002,
        "z": 58
      }
    ],
    "sweep_once": [
      {
        "x": 4,
        "y": 0,
        "z": 2000
      },
      {
        "x": 3,
        "y": 0,
        "z": 5000
      },
      {
        "x": 5,
        "y": 5012001,
        "z": 3
      }
    ],
    "sweep_monster_once": [
      {
        "x": 500,
        "y": 3,
        "z": 5
      }
    ]
  },
  {
    "id": 19,
    "level_id": 10019,
    "block_id": 2,
    "cost": [
      {
        "x": 1,
        "y": 0,
        "z": 5
      }
    ],
    "money": 1450,
    "exp": 580,
    "patrol_unit": 10019,
    "patrol_once": [
      {
        "x": 5,
        "y": 1020000,
        "z": 10
      },
      {
        "x": 5,
        "y": 5012001,
        "z": 2
      },
      {
        "x": 5,
        "y": 1030002,
        "z": 59
      }
    ],
    "sweep_once": [
      {
        "x": 4,
        "y": 0,
        "z": 2000
      },
      {
        "x": 3,
        "y": 0,
        "z": 5000
      },
      {
        "x": 5,
        "y": 5012001,
        "z": 3
      }
    ],
    "sweep_monster_once": [
      {
        "x": 500,
        "y": 3,
        "z": 5
      }
    ]
  },
  {
    "id": 20,
    "level_id": 10020,
    "block_id": 2,
    "cost": [
      {
        "x": 1,
        "y": 0,
        "z": 5
      }
    ],
    "money": 1500,
    "exp": 600,
    "patrol_unit": 10020,
    "patrol_once": [
      {
        "x": 5,
        "y": 1020000,
        "z": 10
      },
      {
        "x": 5,
        "y": 5012001,
        "z": 2
      },
      {
        "x": 5,
        "y": 1030002,
        "z": 60
      }
    ],
    "sweep_once": [
      {
        "x": 4,
        "y": 0,
        "z": 2000
      },
      {
        "x": 3,
        "y": 0,
        "z": 5000
      },
      {
        "x": 5,
        "y": 5012001,
        "z": 3
      }
    ],
    "sweep_monster_once": [
      {
        "x": 500,
        "y": 3,
        "z": 5
      }
    ]
  },
  {
    "id": 21,
    "level_id": 10021,
    "block_id": 3,
    "cost": [
      {
        "x": 1,
        "y": 0,
        "z": 5
      }
    ],
    "money": 1550,
    "exp": 620,
    "patrol_unit": 10021,
    "patrol_once": [
      {
        "x": 5,
        "y": 1020000,
        "z": 10
      },
      {
        "x": 5,
        "y": 5012001,
        "z": 2
      },
      {
        "x": 5,
        "y": 1030002,
        "z": 60
      }
    ],
    "sweep_once": [
      {
        "x": 4,
        "y": 0,
        "z": 2000
      },
      {
        "x": 3,
        "y": 0,
        "z": 5000
      },
      {
        "x": 5,
        "y": 5012001,
        "z": 3
      }
    ],
    "sweep_monster_once": [
      {
        "x": 500,
        "y": 3,
        "z": 5
      }
    ]
  },
  {
    "id": 22,
    "level_id": 10022,
    "block_id": 3,
    "cost": [
      {
        "x": 1,
        "y": 0,
        "z": 5
      }
    ],
    "money": 1600,
    "exp": 640,
    "patrol_unit": 10022,
    "patrol_once": [
      {
        "x": 5,
        "y": 1020000,
        "z": 10
      },
      {
        "x": 5,
        "y": 5012001,
        "z": 2
      },
      {
        "x": 5,
        "y": 1030002,
        "z": 61
      }
    ],
    "sweep_once": [
      {
        "x": 4,
        "y": 0,
        "z": 2000
      },
      {
        "x": 3,
        "y": 0,
        "z": 5000
      },
      {
        "x": 5,
        "y": 5012001,
        "z": 3
      }
    ],
    "sweep_monster_once": [
      {
        "x": 500,
        "y": 3,
        "z": 5
      }
    ]
  },
  {
    "id": 23,
    "level_id": 10023,
    "block_id": 3,
    "cost": [
      {
        "x": 1,
        "y": 0,
        "z": 5
      }
    ],
    "money": 1650,
    "exp": 660,
    "patrol_unit": 10023,
    "patrol_once": [
      {
        "x": 5,
        "y": 1020000,
        "z": 10
      },
      {
        "x": 5,
        "y": 5012001,
        "z": 3
      },
      {
        "x": 5,
        "y": 1030002,
        "z": 61
      }
    ],
    "sweep_once": [
      {
        "x": 4,
        "y": 0,
        "z": 2000
      },
      {
        "x": 3,
        "y": 0,
        "z": 5000
      },
      {
        "x": 5,
        "y": 5012001,
        "z": 3
      }
    ],
    "sweep_monster_once": [
      {
        "x": 500,
        "y": 3,
        "z": 5
      }
    ]
  },
  {
    "id": 24,
    "level_id": 10024,
    "block_id": 3,
    "cost": [
      {
        "x": 1,
        "y": 0,
        "z": 5
      }
    ],
    "money": 1700,
    "exp": 680,
    "patrol_unit": 10024,
    "patrol_once": [
      {
        "x": 5,
        "y": 1020000,
        "z": 10
      },
      {
        "x": 5,
        "y": 5012001,
        "z": 3
      },
      {
        "x": 5,
        "y": 1030002,
        "z": 62
      }
    ],
    "sweep_once": [
      {
        "x": 4,
        "y": 0,
        "z": 2000
      },
      {
        "x": 3,
        "y": 0,
        "z": 5000
      },
      {
        "x": 5,
        "y": 5012001,
        "z": 3
      }
    ],
    "sweep_monster_once": [
      {
        "x": 500,
        "y": 3,
        "z": 5
      }
    ]
  },
  {
    "id": 25,
    "level_id": 10025,
    "block_id": 3,
    "cost": [
      {
        "x": 1,
        "y": 0,
        "z": 5
      }
    ],
    "money": 1750,
    "exp": 700,
    "patrol_unit": 10025,
    "patrol_once": [
      {
        "x": 5,
        "y": 1020000,
        "z": 10
      },
      {
        "x": 5,
        "y": 5012001,
        "z": 3
      },
      {
        "x": 5,
        "y": 1030002,
        "z": 62
      }
    ],
    "sweep_once": [
      {
        "x": 4,
        "y": 0,
        "z": 2000
      },
      {
        "x": 3,
        "y": 0,
        "z": 5000
      },
      {
        "x": 5,
        "y": 5012001,
        "z": 3
      }
    ],
    "sweep_monster_once": [
      {
        "x": 500,
        "y": 3,
        "z": 5
      }
    ]
  },
  {
    "id": 26,
    "level_id": 10026,
    "block_id": 3,
    "cost": [
      {
        "x": 1,
        "y": 0,
        "z": 5
      }
    ],
    "money": 1800,
    "exp": 720,
    "patrol_unit": 10026,
    "patrol_once": [
      {
        "x": 5,
        "y": 1020000,
        "z": 10
      },
      {
        "x": 5,
        "y": 5012001,
        "z": 3
      },
      {
        "x": 5,
        "y": 1030002,
        "z": 62
      }
    ],
    "sweep_once": [
      {
        "x": 4,
        "y": 0,
        "z": 2000
      },
      {
        "x": 3,
        "y": 0,
        "z": 5000
      },
      {
        "x": 5,
        "y": 5012001,
        "z": 3
      }
    ],
    "sweep_monster_once": [
      {
        "x": 500,
        "y": 3,
        "z": 5
      }
    ]
  },
  {
    "id": 27,
    "level_id": 10027,
    "block_id": 3,
    "cost": [
      {
        "x": 1,
        "y": 0,
        "z": 5
      }
    ],
    "money": 1850,
    "exp": 740,
    "patrol_unit": 10027,
    "patrol_once": [
      {
        "x": 5,
        "y": 1020000,
        "z": 11
      },
      {
        "x": 5,
        "y": 5012001,
        "z": 3
      },
      {
        "x": 5,
        "y": 1030002,
        "z": 63
      }
    ],
    "sweep_once": [
      {
        "x": 4,
        "y": 0,
        "z": 2000
      },
      {
        "x": 3,
        "y": 0,
        "z": 5000
      },
      {
        "x": 5,
        "y": 5012001,
        "z": 3
      }
    ],
    "sweep_monster_once": [
      {
        "x": 500,
        "y": 3,
        "z": 5
      }
    ]
  },
  {
    "id": 28,
    "level_id": 10028,
    "block_id": 3,
    "cost": [
      {
        "x": 1,
        "y": 0,
        "z": 5
      }
    ],
    "money": 1900,
    "exp": 760,
    "patrol_unit": 10028,
    "patrol_once": [
      {
        "x": 5,
        "y": 1020000,
        "z": 11
      },
      {
        "x": 5,
        "y": 5012001,
        "z": 3
      },
      {
        "x": 5,
        "y": 1030002,
        "z": 63
      }
    ],
    "sweep_once": [
      {
        "x": 4,
        "y": 0,
        "z": 2000
      },
      {
        "x": 3,
        "y": 0,
        "z": 5000
      },
      {
        "x": 5,
        "y": 5012001,
        "z": 3
      }
    ],
    "sweep_monster_once": [
      {
        "x": 500,
        "y": 3,
        "z": 5
      }
    ]
  },
  {
    "id": 29,
    "level_id": 10029,
    "block_id": 3,
    "cost": [
      {
        "x": 1,
        "y": 0,
        "z": 5
      }
    ],
    "money": 1950,
    "exp": 780,
    "patrol_unit": 10029,
    "patrol_once": [
      {
        "x": 5,
        "y": 1020000,
        "z": 11
      },
      {
        "x": 5,
        "y": 5012001,
        "z": 3
      },
      {
        "x": 5,
        "y": 1030002,
        "z": 63
      }
    ],
    "sweep_once": [
      {
        "x": 4,
        "y": 0,
        "z": 2000
      },
      {
        "x": 3,
        "y": 0,
        "z": 5000
      },
      {
        "x": 5,
        "y": 5012001,
        "z": 3
      }
    ],
    "sweep_monster_once": [
      {
        "x": 500,
        "y": 3,
        "z": 5
      }
    ]
  },
  {
    "id": 30,
    "level_id": 10030,
    "block_id": 3,
    "cost": [
      {
        "x": 1,
        "y": 0,
        "z": 5
      }
    ],
    "money": 2000,
    "exp": 800,
    "patrol_unit": 10030,
    "patrol_once": [
      {
        "x": 5,
        "y": 1020000,
        "z": 11
      },
      {
        "x": 5,
        "y": 5012001,
        "z": 3
      },
      {
        "x": 5,
        "y": 1030002,
        "z": 63
      }
    ],
    "sweep_once": [
      {
        "x": 4,
        "y": 0,
        "z": 2000
      },
      {
        "x": 3,
        "y": 0,
        "z": 5000
      },
      {
        "x": 5,
        "y": 5012001,
        "z": 3
      }
    ],
    "sweep_monster_once": [
      {
        "x": 500,
        "y": 3,
        "z": 5
      }
    ]
  },
  {
    "id": 31,
    "level_id": 10031,
    "block_id": 4,
    "cost": [
      {
        "x": 1,
        "y": 0,
        "z": 5
      }
    ],
    "money": 2050,
    "exp": 820,
    "patrol_unit": 10031,
    "patrol_once": [
      {
        "x": 5,
        "y": 1020000,
        "z": 11
      },
      {
        "x": 5,
        "y": 5012001,
        "z": 3
      },
      {
        "x": 5,
        "y": 1030002,
        "z": 64
      }
    ],
    "sweep_once": [
      {
        "x": 4,
        "y": 0,
        "z": 2000
      },
      {
        "x": 3,
        "y": 0,
        "z": 5000
      },
      {
        "x": 5,
        "y": 5012001,
        "z": 3
      }
    ],
    "sweep_monster_once": [
      {
        "x": 500,
        "y": 3,
        "z": 5
      }
    ]
  },
  {
    "id": 32,
    "level_id": 10032,
    "block_id": 4,
    "cost": [
      {
        "x": 1,
        "y": 0,
        "z": 5
      }
    ],
    "money": 2100,
    "exp": 840,
    "patrol_unit": 10032,
    "patrol_once": [
      {
        "x": 5,
        "y": 1020000,
        "z": 11
      },
      {
        "x": 5,
        "y": 5012001,
        "z": 3
      },
      {
        "x": 5,
        "y": 1030002,
        "z": 64
      }
    ],
    "sweep_once": [
      {
        "x": 4,
        "y": 0,
        "z": 2000
      },
      {
        "x": 3,
        "y": 0,
        "z": 5000
      },
      {
        "x": 5,
        "y": 5012001,
        "z": 3
      }
    ],
    "sweep_monster_once": [
      {
        "x": 500,
        "y": 3,
        "z": 5
      }
    ]
  },
  {
    "id": 33,
    "level_id": 10033,
    "block_id": 4,
    "cost": [
      {
        "x": 1,
        "y": 0,
        "z": 5
      }
    ],
    "money": 2150,
    "exp": 860,
    "patrol_unit": 10033,
    "patrol_once": [
      {
        "x": 5,
        "y": 1020000,
        "z": 11
      },
      {
        "x": 5,
        "y": 5012001,
        "z": 3
      },
      {
        "x": 5,
        "y": 1030002,
        "z": 64
      }
    ],
    "sweep_once": [
      {
        "x": 4,
        "y": 0,
        "z": 2000
      },
      {
        "x": 3,
        "y": 0,
        "z": 5000
      },
      {
        "x": 5,
        "y": 5012001,
        "z": 3
      }
    ],
    "sweep_monster_once": [
      {
        "x": 500,
        "y": 3,
        "z": 5
      }
    ]
  },
  {
    "id": 34,
    "level_id": 10034,
    "block_id": 4,
    "cost": [
      {
        "x": 1,
        "y": 0,
        "z": 5
      }
    ],
    "money": 2200,
    "exp": 880,
    "patrol_unit": 10034,
    "patrol_once": [
      {
        "x": 5,
        "y": 1020000,
        "z": 11
      },
      {
        "x": 5,
        "y": 5012001,
        "z": 3
      },
      {
        "x": 5,
        "y": 1030002,
        "z": 64
      }
    ],
    "sweep_once": [
      {
        "x": 4,
        "y": 0,
        "z": 2000
      },
      {
        "x": 3,
        "y": 0,
        "z": 5000
      },
      {
        "x": 5,
        "y": 5012001,
        "z": 3
      }
    ],
    "sweep_monster_once": [
      {
        "x": 500,
        "y": 3,
        "z": 5
      }
    ]
  },
  {
    "id": 35,
    "level_id": 10035,
    "block_id": 4,
    "cost": [
      {
        "x": 1,
        "y": 0,
        "z": 5
      }
    ],
    "money": 2250,
    "exp": 900,
    "patrol_unit": 10035,
    "patrol_once": [
      {
        "x": 5,
        "y": 1020000,
        "z": 11
      },
      {
        "x": 5,
        "y": 5012001,
        "z": 3
      },
      {
        "x": 5,
        "y": 1030002,
        "z": 64
      }
    ],
    "sweep_once": [
      {
        "x": 4,
        "y": 0,
        "z": 2000
      },
      {
        "x": 3,
        "y": 0,
        "z": 5000
      },
      {
        "x": 5,
        "y": 5012001,
        "z": 3
      }
    ],
    "sweep_monster_once": [
      {
        "x": 500,
        "y": 3,
        "z": 5
      }
    ]
  },
  {
    "id": 36,
    "level_id": 10036,
    "block_id": 4,
    "cost": [
      {
        "x": 1,
        "y": 0,
        "z": 5
      }
    ],
    "money": 2300,
    "exp": 920,
    "patrol_unit": 10036,
    "patrol_once": [
      {
        "x": 5,
        "y": 1020000,
        "z": 11
      },
      {
        "x": 5,
        "y": 5012001,
        "z": 4
      },
      {
        "x": 5,
        "y": 1030002,
        "z": 65
      }
    ],
    "sweep_once": [
      {
        "x": 4,
        "y": 0,
        "z": 2000
      },
      {
        "x": 3,
        "y": 0,
        "z": 5000
      },
      {
        "x": 5,
        "y": 5012001,
        "z": 3
      }
    ],
    "sweep_monster_once": [
      {
        "x": 500,
        "y": 3,
        "z": 5
      }
    ]
  },
  {
    "id": 37,
    "level_id": 10037,
    "block_id": 4,
    "cost": [
      {
        "x": 1,
        "y": 0,
        "z": 5
      }
    ],
    "money": 2350,
    "exp": 940,
    "patrol_unit": 10037,
    "patrol_once": [
      {
        "x": 5,
        "y": 1020000,
        "z": 12
      },
      {
        "x": 5,
        "y": 5012001,
        "z": 4
      },
      {
        "x": 5,
        "y": 1030002,
        "z": 65
      }
    ],
    "sweep_once": [
      {
        "x": 4,
        "y": 0,
        "z": 2000
      },
      {
        "x": 3,
        "y": 0,
        "z": 5000
      },
      {
        "x": 5,
        "y": 5012001,
        "z": 3
      }
    ],
    "sweep_monster_once": [
      {
        "x": 500,
        "y": 3,
        "z": 5
      }
    ]
  },
  {
    "id": 38,
    "level_id": 10038,
    "block_id": 4,
    "cost": [
      {
        "x": 1,
        "y": 0,
        "z": 5
      }
    ],
    "money": 2400,
    "exp": 960,
    "patrol_unit": 10038,
    "patrol_once": [
      {
        "x": 5,
        "y": 1020000,
        "z": 12
      },
      {
        "x": 5,
        "y": 5012001,
        "z": 4
      },
      {
        "x": 5,
        "y": 1030002,
        "z": 65
      }
    ],
    "sweep_once": [
      {
        "x": 4,
        "y": 0,
        "z": 2000
      },
      {
        "x": 3,
        "y": 0,
        "z": 5000
      },
      {
        "x": 5,
        "y": 5012001,
        "z": 3
      }
    ],
    "sweep_monster_once": [
      {
        "x": 500,
        "y": 3,
        "z": 5
      }
    ]
  },
  {
    "id": 39,
    "level_id": 10039,
    "block_id": 4,
    "cost": [
      {
        "x": 1,
        "y": 0,
        "z": 5
      }
    ],
    "money": 2450,
    "exp": 980,
    "patrol_unit": 10039,
    "patrol_once": [
      {
        "x": 5,
        "y": 1020000,
        "z": 12
      },
      {
        "x": 5,
        "y": 5012001,
        "z": 4
      },
      {
        "x": 5,
        "y": 1030002,
        "z": 65
      }
    ],
    "sweep_once": [
      {
        "x": 4,
        "y": 0,
        "z": 2000
      },
      {
        "x": 3,
        "y": 0,
        "z": 5000
      },
      {
        "x": 5,
        "y": 5012001,
        "z": 3
      }
    ],
    "sweep_monster_once": [
      {
        "x": 500,
        "y": 3,
        "z": 5
      }
    ]
  },
  {
    "id": 40,
    "level_id": 10040,
    "block_id": 4,
    "cost": [
      {
        "x": 1,
        "y": 0,
        "z": 5
      }
    ],
    "money": 2500,
    "exp": 1000,
    "patrol_unit": 10040,
    "patrol_once": [
      {
        "x": 5,
        "y": 1020000,
        "z": 12
      },
      {
        "x": 5,
        "y": 5012001,
        "z": 4
      },
      {
        "x": 5,
        "y": 1030002,
        "z": 65
      }
    ],
    "sweep_once": [
      {
        "x": 4,
        "y": 0,
        "z": 2000
      },
      {
        "x": 3,
        "y": 0,
        "z": 5000
      },
      {
        "x": 5,
        "y": 5012001,
        "z": 3
      }
    ],
    "sweep_monster_once": [
      {
        "x": 500,
        "y": 3,
        "z": 5
      }
    ]
  },
  {
    "id": 41,
    "level_id": 10041,
    "block_id": 5,
    "cost": [
      {
        "x": 1,
        "y": 0,
        "z": 5
      }
    ],
    "money": 2550,
    "exp": 1020,
    "patrol_unit": 10041,
    "patrol_once": [
      {
        "x": 5,
        "y": 1020000,
        "z": 12
      },
      {
        "x": 5,
        "y": 5012001,
        "z": 4
      },
      {
        "x": 5,
        "y": 1030002,
        "z": 65
      }
    ],
    "sweep_once": [
      {
        "x": 4,
        "y": 0,
        "z": 2000
      },
      {
        "x": 3,
        "y": 0,
        "z": 5000
      },
      {
        "x": 5,
        "y": 5012001,
        "z": 3
      }
    ],
    "sweep_monster_once": [
      {
        "x": 500,
        "y": 3,
        "z": 5
      }
    ]
  },
  {
    "id": 42,
    "level_id": 10042,
    "block_id": 5,
    "cost": [
      {
        "x": 1,
        "y": 0,
        "z": 5
      }
    ],
    "money": 2600,
    "exp": 1040,
    "patrol_unit": 10042,
    "patrol_once": [
      {
        "x": 5,
        "y": 1020000,
        "z": 12
      },
      {
        "x": 5,
        "y": 5012001,
        "z": 4
      },
      {
        "x": 5,
        "y": 1030002,
        "z": 66
      }
    ],
    "sweep_once": [
      {
        "x": 4,
        "y": 0,
        "z": 2000
      },
      {
        "x": 3,
        "y": 0,
        "z": 5000
      },
      {
        "x": 5,
        "y": 5012001,
        "z": 3
      }
    ],
    "sweep_monster_once": [
      {
        "x": 500,
        "y": 3,
        "z": 5
      }
    ]
  },
  {
    "id": 43,
    "level_id": 10043,
    "block_id": 5,
    "cost": [
      {
        "x": 1,
        "y": 0,
        "z": 5
      }
    ],
    "money": 2650,
    "exp": 1060,
    "patrol_unit": 10043,
    "patrol_once": [
      {
        "x": 5,
        "y": 1020000,
        "z": 12
      },
      {
        "x": 5,
        "y": 5012001,
        "z": 4
      },
      {
        "x": 5,
        "y": 1030002,
        "z": 66
      }
    ],
    "sweep_once": [
      {
        "x": 4,
        "y": 0,
        "z": 2000
      },
      {
        "x": 3,
        "y": 0,
        "z": 5000
      },
      {
        "x": 5,
        "y": 5012001,
        "z": 3
      }
    ],
    "sweep_monster_once": [
      {
        "x": 500,
        "y": 3,
        "z": 5
      }
    ]
  },
  {
    "id": 44,
    "level_id": 10044,
    "block_id": 5,
    "cost": [
      {
        "x": 1,
        "y": 0,
        "z": 5
      }
    ],
    "money": 2700,
    "exp": 1080,
    "patrol_unit": 10044,
    "patrol_once": [
      {
        "x": 5,
        "y": 1020000,
        "z": 12
      },
      {
        "x": 5,
        "y": 5012001,
        "z": 4
      },
      {
        "x": 5,
        "y": 1030002,
        "z": 66
      }
    ],
    "sweep_once": [
      {
        "x": 4,
        "y": 0,
        "z": 2000
      },
      {
        "x": 3,
        "y": 0,
        "z": 5000
      },
      {
        "x": 5,
        "y": 5012001,
        "z": 3
      }
    ],
    "sweep_monster_once": [
      {
        "x": 500,
        "y": 3,
        "z": 5
      }
    ]
  },
  {
    "id": 45,
    "level_id": 10045,
    "block_id": 5,
    "cost": [
      {
        "x": 1,
        "y": 0,
        "z": 5
      }
    ],
    "money": 2750,
    "exp": 1100,
    "patrol_unit": 10045,
    "patrol_once": [
      {
        "x": 5,
        "y": 1020000,
        "z": 12
      },
      {
        "x": 5,
        "y": 5012001,
        "z": 4
      },
      {
        "x": 5,
        "y": 1030002,
        "z": 66
      }
    ],
    "sweep_once": [
      {
        "x": 4,
        "y": 0,
        "z": 2000
      },
      {
        "x": 3,
        "y": 0,
        "z": 5000
      },
      {
        "x": 5,
        "y": 5012001,
        "z": 3
      }
    ],
    "sweep_monster_once": [
      {
        "x": 500,
        "y": 3,
        "z": 5
      }
    ]
  },
  {
    "id": 46,
    "level_id": 10046,
    "block_id": 5,
    "cost": [
      {
        "x": 1,
        "y": 0,
        "z": 5
      }
    ],
    "money": 2800,
    "exp": 1120,
    "patrol_unit": 10046,
    "patrol_once": [
      {
        "x": 5,
        "y": 1020000,
        "z": 12
      },
      {
        "x": 5,
        "y": 5012001,
        "z": 4
      },
      {
        "x": 5,
        "y": 1030002,
        "z": 66
      }
    ],
    "sweep_once": [
      {
        "x": 4,
        "y": 0,
        "z": 2000
      },
      {
        "x": 3,
        "y": 0,
        "z": 5000
      },
      {
        "x": 5,
        "y": 5012001,
        "z": 3
      }
    ],
    "sweep_monster_once": [
      {
        "x": 500,
        "y": 3,
        "z": 5
      }
    ]
  },
  {
    "id": 47,
    "level_id": 10047,
    "block_id": 5,
    "cost": [
      {
        "x": 1,
        "y": 0,
        "z": 5
      }
    ],
    "money": 2850,
    "exp": 1140,
    "patrol_unit": 10047,
    "patrol_once": [
      {
        "x": 5,
        "y": 1020000,
        "z": 13
      },
      {
        "x": 5,
        "y": 5012001,
        "z": 4
      },
      {
        "x": 5,
        "y": 1030002,
        "z": 66
      }
    ],
    "sweep_once": [
      {
        "x": 4,
        "y": 0,
        "z": 2000
      },
      {
        "x": 3,
        "y": 0,
        "z": 5000
      },
      {
        "x": 5,
        "y": 5012001,
        "z": 3
      }
    ],
    "sweep_monster_once": [
      {
        "x": 500,
        "y": 3,
        "z": 5
      }
    ]
  },
  {
    "id": 48,
    "level_id": 10048,
    "block_id": 5,
    "cost": [
      {
        "x": 1,
        "y": 0,
        "z": 5
      }
    ],
    "money": 2900,
    "exp": 1160,
    "patrol_unit": 10048,
    "patrol_once": [
      {
        "x": 5,
        "y": 1020000,
        "z": 13
      },
      {
        "x": 5,
        "y": 5012001,
        "z": 4
      },
      {
        "x": 5,
        "y": 1030002,
        "z": 67
      }
    ],
    "sweep_once": [
      {
        "x": 4,
        "y": 0,
        "z": 2000
      },
      {
        "x": 3,
        "y": 0,
        "z": 5000
      },
      {
        "x": 5,
        "y": 5012001,
        "z": 3
      }
    ],
    "sweep_monster_once": [
      {
        "x": 500,
        "y": 3,
        "z": 5
      }
    ]
  },
  {
    "id": 49,
    "level_id": 10049,
    "block_id": 5,
    "cost": [
      {
        "x": 1,
        "y": 0,
        "z": 5
      }
    ],
    "money": 2950,
    "exp": 1180,
    "patrol_unit": 10049,
    "patrol_once": [
      {
        "x": 5,
        "y": 1020000,
        "z": 13
      },
      {
        "x": 5,
        "y": 5012001,
        "z": 4
      },
      {
        "x": 5,
        "y": 1030002,
        "z": 67
      }
    ],
    "sweep_once": [
      {
        "x": 4,
        "y": 0,
        "z": 2000
      },
      {
        "x": 3,
        "y": 0,
        "z": 5000
      },
      {
        "x": 5,
        "y": 5012001,
        "z": 3
      }
    ],
    "sweep_monster_once": [
      {
        "x": 500,
        "y": 3,
        "z": 5
      }
    ]
  },
  {
    "id": 50,
    "level_id": 10050,
    "block_id": 5,
    "cost": [
      {
        "x": 1,
        "y": 0,
        "z": 5
      }
    ],
    "money": 3000,
    "exp": 1200,
    "patrol_unit": 10050,
    "patrol_once": [
      {
        "x": 5,
        "y": 1020000,
        "z": 13
      },
      {
        "x": 5,
        "y": 5012001,
        "z": 5
      },
      {
        "x": 5,
        "y": 1030002,
        "z": 67
      }
    ],
    "sweep_once": [
      {
        "x": 4,
        "y": 0,
        "z": 2000
      },
      {
        "x": 3,
        "y": 0,
        "z": 5000
      },
      {
        "x": 5,
        "y": 5012001,
        "z": 3
      }
    ],
    "sweep_monster_once": [
      {
        "x": 500,
        "y": 3,
        "z": 5
      }
    ]
  },
  {
    "id": 51,
    "level_id": 10051,
    "block_id": 6,
    "cost": [
      {
        "x": 1,
        "y": 0,
        "z": 5
      }
    ],
    "money": 3050,
    "exp": 1220,
    "patrol_unit": 10051,
    "patrol_once": [
      {
        "x": 5,
        "y": 1020000,
        "z": 13
      },
      {
        "x": 5,
        "y": 5012001,
        "z": 5
      },
      {
        "x": 5,
        "y": 1030002,
        "z": 67
      }
    ],
    "sweep_once": [
      {
        "x": 4,
        "y": 0,
        "z": 2000
      },
      {
        "x": 3,
        "y": 0,
        "z": 5000
      },
      {
        "x": 5,
        "y": 5012001,
        "z": 3
      }
    ],
    "sweep_monster_once": [
      {
        "x": 500,
        "y": 3,
        "z": 5
      }
    ]
  },
  {
    "id": 52,
    "level_id": 10052,
    "block_id": 6,
    "cost": [
      {
        "x": 1,
        "y": 0,
        "z": 5
      }
    ],
    "money": 3100,
    "exp": 1240,
    "patrol_unit": 10052,
    "patrol_once": [
      {
        "x": 5,
        "y": 1020000,
        "z": 13
      },
      {
        "x": 5,
        "y": 5012001,
        "z": 5
      },
      {
        "x": 5,
        "y": 1030002,
        "z": 67
      }
    ],
    "sweep_once": [
      {
        "x": 4,
        "y": 0,
        "z": 2000
      },
      {
        "x": 3,
        "y": 0,
        "z": 5000
      },
      {
        "x": 5,
        "y": 5012001,
        "z": 3
      }
    ],
    "sweep_monster_once": [
      {
        "x": 500,
        "y": 3,
        "z": 5
      }
    ]
  },
  {
    "id": 53,
    "level_id": 10053,
    "block_id": 6,
    "cost": [
      {
        "x": 1,
        "y": 0,
        "z": 5
      }
    ],
    "money": 3150,
    "exp": 1260,
    "patrol_unit": 10053,
    "patrol_once": [
      {
        "x": 5,
        "y": 1020000,
        "z": 13
      },
      {
        "x": 5,
        "y": 5012001,
        "z": 5
      },
      {
        "x": 5,
        "y": 1030002,
        "z": 67
      }
    ],
    "sweep_once": [
      {
        "x": 4,
        "y": 0,
        "z": 2000
      },
      {
        "x": 3,
        "y": 0,
        "z": 5000
      },
      {
        "x": 5,
        "y": 5012001,
        "z": 3
      }
    ],
    "sweep_monster_once": [
      {
        "x": 500,
        "y": 3,
        "z": 5
      }
    ]
  },
  {
    "id": 54,
    "level_id": 10054,
    "block_id": 6,
    "cost": [
      {
        "x": 1,
        "y": 0,
        "z": 5
      }
    ],
    "money": 3200,
    "exp": 1280,
    "patrol_unit": 10054,
    "patrol_once": [
      {
        "x": 5,
        "y": 1020000,
        "z": 13
      },
      {
        "x": 5,
        "y": 5012001,
        "z": 5
      },
      {
        "x": 5,
        "y": 1030002,
        "z": 68
      }
    ],
    "sweep_once": [
      {
        "x": 4,
        "y": 0,
        "z": 2000
      },
      {
        "x": 3,
        "y": 0,
        "z": 5000
      },
      {
        "x": 5,
        "y": 5012001,
        "z": 3
      }
    ],
    "sweep_monster_once": [
      {
        "x": 500,
        "y": 3,
        "z": 5
      }
    ]
  },
  {
    "id": 55,
    "level_id": 10055,
    "block_id": 6,
    "cost": [
      {
        "x": 1,
        "y": 0,
        "z": 5
      }
    ],
    "money": 3250,
    "exp": 1300,
    "patrol_unit": 10055,
    "patrol_once": [
      {
        "x": 5,
        "y": 1020000,
        "z": 13
      },
      {
        "x": 5,
        "y": 5012001,
        "z": 5
      },
      {
        "x": 5,
        "y": 1030002,
        "z": 68
      }
    ],
    "sweep_once": [
      {
        "x": 4,
        "y": 0,
        "z": 2000
      },
      {
        "x": 3,
        "y": 0,
        "z": 5000
      },
      {
        "x": 5,
        "y": 5012001,
        "z": 3
      }
    ],
    "sweep_monster_once": [
      {
        "x": 500,
        "y": 3,
        "z": 5
      }
    ]
  },
  {
    "id": 56,
    "level_id": 10056,
    "block_id": 6,
    "cost": [
      {
        "x": 1,
        "y": 0,
        "z": 5
      }
    ],
    "money": 3300,
    "exp": 1320,
    "patrol_unit": 10056,
    "patrol_once": [
      {
        "x": 5,
        "y": 1020000,
        "z": 13
      },
      {
        "x": 5,
        "y": 5012001,
        "z": 5
      },
      {
        "x": 5,
        "y": 1030002,
        "z": 68
      }
    ],
    "sweep_once": [
      {
        "x": 4,
        "y": 0,
        "z": 2000
      },
      {
        "x": 3,
        "y": 0,
        "z": 5000
      },
      {
        "x": 5,
        "y": 5012001,
        "z": 3
      }
    ],
    "sweep_monster_once": [
      {
        "x": 500,
        "y": 3,
        "z": 5
      }
    ]
  },
  {
    "id": 57,
    "level_id": 10057,
    "block_id": 6,
    "cost": [
      {
        "x": 1,
        "y": 0,
        "z": 5
      }
    ],
    "money": 3350,
    "exp": 1340,
    "patrol_unit": 10057,
    "patrol_once": [
      {
        "x": 5,
        "y": 1020000,
        "z": 13
      },
      {
        "x": 5,
        "y": 5012001,
        "z": 5
      },
      {
        "x": 5,
        "y": 1030002,
        "z": 68
      }
    ],
    "sweep_once": [
      {
        "x": 4,
        "y": 0,
        "z": 2000
      },
      {
        "x": 3,
        "y": 0,
        "z": 5000
      },
      {
        "x": 5,
        "y": 5012001,
        "z": 3
      }
    ],
    "sweep_monster_once": [
      {
        "x": 500,
        "y": 3,
        "z": 5
      }
    ]
  },
  {
    "id": 58,
    "level_id": 10058,
    "block_id": 6,
    "cost": [
      {
        "x": 1,
        "y": 0,
        "z": 5
      }
    ],
    "money": 3400,
    "exp": 1360,
    "patrol_unit": 10058,
    "patrol_once": [
      {
        "x": 5,
        "y": 1020000,
        "z": 13
      },
      {
        "x": 5,
        "y": 5012001,
        "z": 5
      },
      {
        "x": 5,
        "y": 1030002,
        "z": 68
      }
    ],
    "sweep_once": [
      {
        "x": 4,
        "y": 0,
        "z": 2000
      },
      {
        "x": 3,
        "y": 0,
        "z": 5000
      },
      {
        "x": 5,
        "y": 5012001,
        "z": 3
      }
    ],
    "sweep_monster_once": [
      {
        "x": 500,
        "y": 3,
        "z": 5
      }
    ]
  },
  {
    "id": 59,
    "level_id": 10059,
    "block_id": 6,
    "cost": [
      {
        "x": 1,
        "y": 0,
        "z": 5
      }
    ],
    "money": 3450,
    "exp": 1380,
    "patrol_unit": 10059,
    "patrol_once": [
      {
        "x": 5,
        "y": 1020000,
        "z": 13
      },
      {
        "x": 5,
        "y": 5012001,
        "z": 5
      },
      {
        "x": 5,
        "y": 1030002,
        "z": 68
      }
    ],
    "sweep_once": [
      {
        "x": 4,
        "y": 0,
        "z": 2000
      },
      {
        "x": 3,
        "y": 0,
        "z": 5000
      },
      {
        "x": 5,
        "y": 5012001,
        "z": 3
      }
    ],
    "sweep_monster_once": [
      {
        "x": 500,
        "y": 3,
        "z": 5
      }
    ]
  },
  {
    "id": 60,
    "level_id": 10060,
    "block_id": 6,
    "cost": [
      {
        "x": 1,
        "y": 0,
        "z": 5
      }
    ],
    "money": 3500,
    "exp": 1400,
    "patrol_unit": 10060,
    "patrol_once": [
      {
        "x": 5,
        "y": 1020000,
        "z": 13
      },
      {
        "x": 5,
        "y": 5012001,
        "z": 5
      },
      {
        "x": 5,
        "y": 1030002,
        "z": 68
      }
    ],
    "sweep_once": [
      {
        "x": 4,
        "y": 0,
        "z": 2000
      },
      {
        "x": 3,
        "y": 0,
        "z": 5000
      },
      {
        "x": 5,
        "y": 5012001,
        "z": 3
      }
    ],
    "sweep_monster_once": [
      {
        "x": 500,
        "y": 3,
        "z": 5
      }
    ]
  },
  {
    "id": 61,
    "level_id": 10061,
    "block_id": 7,
    "cost": [
      {
        "x": 1,
        "y": 0,
        "z": 5
      }
    ],
    "money": 3550,
    "exp": 1420,
    "patrol_unit": 10061,
    "patrol_once": [
      {
        "x": 5,
        "y": 1020000,
        "z": 14
      },
      {
        "x": 5,
        "y": 5012001,
        "z": 5
      },
      {
        "x": 5,
        "y": 1030002,
        "z": 69
      }
    ],
    "sweep_once": [
      {
        "x": 4,
        "y": 0,
        "z": 2000
      },
      {
        "x": 3,
        "y": 0,
        "z": 5000
      },
      {
        "x": 5,
        "y": 5012001,
        "z": 3
      }
    ],
    "sweep_monster_once": [
      {
        "x": 500,
        "y": 3,
        "z": 5
      }
    ]
  },
  {
    "id": 62,
    "level_id": 10062,
    "block_id": 7,
    "cost": [
      {
        "x": 1,
        "y": 0,
        "z": 5
      }
    ],
    "money": 3600,
    "exp": 1440,
    "patrol_unit": 10062,
    "patrol_once": [
      {
        "x": 5,
        "y": 1020000,
        "z": 14
      },
      {
        "x": 5,
        "y": 5012001,
        "z": 5
      },
      {
        "x": 5,
        "y": 1030002,
        "z": 69
      }
    ],
    "sweep_once": [
      {
        "x": 4,
        "y": 0,
        "z": 2000
      },
      {
        "x": 3,
        "y": 0,
        "z": 5000
      },
      {
        "x": 5,
        "y": 5012001,
        "z": 3
      }
    ],
    "sweep_monster_once": [
      {
        "x": 500,
        "y": 3,
        "z": 5
      }
    ]
  },
  {
    "id": 63,
    "level_id": 10063,
    "block_id": 7,
    "cost": [
      {
        "x": 1,
        "y": 0,
        "z": 5
      }
    ],
    "money": 3650,
    "exp": 1460,
    "patrol_unit": 10063,
    "patrol_once": [
      {
        "x": 5,
        "y": 1020000,
        "z": 14
      },
      {
        "x": 5,
        "y": 5012001,
        "z": 5
      },
      {
        "x": 5,
        "y": 1030002,
        "z": 69
      }
    ],
    "sweep_once": [
      {
        "x": 4,
        "y": 0,
        "z": 2000
      },
      {
        "x": 3,
        "y": 0,
        "z": 5000
      },
      {
        "x": 5,
        "y": 5012001,
        "z": 3
      }
    ],
    "sweep_monster_once": [
      {
        "x": 500,
        "y": 3,
        "z": 5
      }
    ]
  },
  {
    "id": 64,
    "level_id": 10064,
    "block_id": 7,
    "cost": [
      {
        "x": 1,
        "y": 0,
        "z": 5
      }
    ],
    "money": 3700,
    "exp": 1480,
    "patrol_unit": 10064,
    "patrol_once": [
      {
        "x": 5,
        "y": 1020000,
        "z": 14
      },
      {
        "x": 5,
        "y": 5012001,
        "z": 5
      },
      {
        "x": 5,
        "y": 1030002,
        "z": 69
      }
    ],
    "sweep_once": [
      {
        "x": 4,
        "y": 0,
        "z": 2000
      },
      {
        "x": 3,
        "y": 0,
        "z": 5000
      },
      {
        "x": 5,
        "y": 5012001,
        "z": 3
      }
    ],
    "sweep_monster_once": [
      {
        "x": 500,
        "y": 3,
        "z": 5
      }
    ]
  },
  {
    "id": 65,
    "level_id": 10065,
    "block_id": 7,
    "cost": [
      {
        "x": 1,
        "y": 0,
        "z": 5
      }
    ],
    "money": 3750,
    "exp": 1500,
    "patrol_unit": 10065,
    "patrol_once": [
      {
        "x": 5,
        "y": 1020000,
        "z": 14
      },
      {
        "x": 5,
        "y": 5012001,
        "z": 5
      },
      {
        "x": 5,
        "y": 1030002,
        "z": 69
      }
    ],
    "sweep_once": [
      {
        "x": 4,
        "y": 0,
        "z": 2000
      },
      {
        "x": 3,
        "y": 0,
        "z": 5000
      },
      {
        "x": 5,
        "y": 5012001,
        "z": 3
      }
    ],
    "sweep_monster_once": [
      {
        "x": 500,
        "y": 3,
        "z": 5
      }
    ]
  },
  {
    "id": 66,
    "level_id": 10066,
    "block_id": 7,
    "cost": [
      {
        "x": 1,
        "y": 0,
        "z": 5
      }
    ],
    "money": 3800,
    "exp": 1520,
    "patrol_unit": 10066,
    "patrol_once": [
      {
        "x": 5,
        "y": 1020000,
        "z": 14
      },
      {
        "x": 5,
        "y": 5012001,
        "z": 5
      },
      {
        "x": 5,
        "y": 1030002,
        "z": 69
      }
    ],
    "sweep_once": [
      {
        "x": 4,
        "y": 0,
        "z": 2000
      },
      {
        "x": 3,
        "y": 0,
        "z": 5000
      },
      {
        "x": 5,
        "y": 5012001,
        "z": 3
      }
    ],
    "sweep_monster_once": [
      {
        "x": 500,
        "y": 3,
        "z": 5
      }
    ]
  },
  {
    "id": 67,
    "level_id": 10067,
    "block_id": 7,
    "cost": [
      {
        "x": 1,
        "y": 0,
        "z": 5
      }
    ],
    "money": 3850,
    "exp": 1540,
    "patrol_unit": 10067,
    "patrol_once": [
      {
        "x": 5,
        "y": 1020000,
        "z": 14
      },
      {
        "x": 5,
        "y": 5012001,
        "z": 5
      },
      {
        "x": 5,
        "y": 1030002,
        "z": 69
      }
    ],
    "sweep_once": [
      {
        "x": 4,
        "y": 0,
        "z": 2000
      },
      {
        "x": 3,
        "y": 0,
        "z": 5000
      },
      {
        "x": 5,
        "y": 5012001,
        "z": 3
      }
    ],
    "sweep_monster_once": [
      {
        "x": 500,
        "y": 3,
        "z": 5
      }
    ]
  },
  {
    "id": 68,
    "level_id": 10068,
    "block_id": 7,
    "cost": [
      {
        "x": 1,
        "y": 0,
        "z": 5
      }
    ],
    "money": 3900,
    "exp": 1560,
    "patrol_unit": 10068,
    "patrol_once": [
      {
        "x": 5,
        "y": 1020000,
        "z": 14
      },
      {
        "x": 5,
        "y": 5012001,
        "z": 5
      },
      {
        "x": 5,
        "y": 1030002,
        "z": 70
      }
    ],
    "sweep_once": [
      {
        "x": 4,
        "y": 0,
        "z": 2000
      },
      {
        "x": 3,
        "y": 0,
        "z": 5000
      },
      {
        "x": 5,
        "y": 5012001,
        "z": 3
      }
    ],
    "sweep_monster_once": [
      {
        "x": 500,
        "y": 3,
        "z": 5
      }
    ]
  },
  {
    "id": 69,
    "level_id": 10069,
    "block_id": 7,
    "cost": [
      {
        "x": 1,
        "y": 0,
        "z": 5
      }
    ],
    "money": 3950,
    "exp": 1580,
    "patrol_unit": 10069,
    "patrol_once": [
      {
        "x": 5,
        "y": 1020000,
        "z": 14
      },
      {
        "x": 5,
        "y": 5012001,
        "z": 5
      },
      {
        "x": 5,
        "y": 1030002,
        "z": 70
      }
    ],
    "sweep_once": [
      {
        "x": 4,
        "y": 0,
        "z": 2000
      },
      {
        "x": 3,
        "y": 0,
        "z": 5000
      },
      {
        "x": 5,
        "y": 5012001,
        "z": 3
      }
    ],
    "sweep_monster_once": [
      {
        "x": 500,
        "y": 3,
        "z": 5
      }
    ]
  },
  {
    "id": 70,
    "level_id": 10070,
    "block_id": 7,
    "cost": [
      {
        "x": 1,
        "y": 0,
        "z": 5
      }
    ],
    "money": 4000,
    "exp": 1600,
    "patrol_unit": 10070,
    "patrol_once": [
      {
        "x": 5,
        "y": 1020000,
        "z": 14
      },
      {
        "x": 5,
        "y": 5012001,
        "z": 5
      },
      {
        "x": 5,
        "y": 1030002,
        "z": 70
      }
    ],
    "sweep_once": [
      {
        "x": 4,
        "y": 0,
        "z": 2000
      },
      {
        "x": 3,
        "y": 0,
        "z": 5000
      },
      {
        "x": 5,
        "y": 5012001,
        "z": 3
      }
    ],
    "sweep_monster_once": [
      {
        "x": 500,
        "y": 3,
        "z": 5
      }
    ]
  },
  {
    "id": 71,
    "level_id": 10071,
    "block_id": 8,
    "cost": [
      {
        "x": 1,
        "y": 0,
        "z": 5
      }
    ],
    "money": 4050,
    "exp": 1620,
    "patrol_unit": 10071,
    "patrol_once": [
      {
        "x": 5,
        "y": 1020000,
        "z": 14
      },
      {
        "x": 5,
        "y": 5012001,
        "z": 5
      },
      {
        "x": 5,
        "y": 1030002,
        "z": 70
      }
    ],
    "sweep_once": [
      {
        "x": 4,
        "y": 0,
        "z": 2000
      },
      {
        "x": 3,
        "y": 0,
        "z": 5000
      },
      {
        "x": 5,
        "y": 5012001,
        "z": 3
      }
    ],
    "sweep_monster_once": [
      {
        "x": 500,
        "y": 3,
        "z": 5
      }
    ]
  },
  {
    "id": 72,
    "level_id": 10072,
    "block_id": 8,
    "cost": [
      {
        "x": 1,
        "y": 0,
        "z": 5
      }
    ],
    "money": 4100,
    "exp": 1640,
    "patrol_unit": 10072,
    "patrol_once": [
      {
        "x": 5,
        "y": 1020000,
        "z": 14
      },
      {
        "x": 5,
        "y": 5012001,
        "z": 5
      },
      {
        "x": 5,
        "y": 1030002,
        "z": 70
      }
    ],
    "sweep_once": [
      {
        "x": 4,
        "y": 0,
        "z": 2000
      },
      {
        "x": 3,
        "y": 0,
        "z": 5000
      },
      {
        "x": 5,
        "y": 5012001,
        "z": 3
      }
    ],
    "sweep_monster_once": [
      {
        "x": 500,
        "y": 3,
        "z": 5
      }
    ]
  },
  {
    "id": 73,
    "level_id": 10073,
    "block_id": 8,
    "cost": [
      {
        "x": 1,
        "y": 0,
        "z": 5
      }
    ],
    "money": 4150,
    "exp": 1660,
    "patrol_unit": 10073,
    "patrol_once": [
      {
        "x": 5,
        "y": 1020000,
        "z": 14
      },
      {
        "x": 5,
        "y": 5012001,
        "z": 5
      },
      {
        "x": 5,
        "y": 1030002,
        "z": 70
      }
    ],
    "sweep_once": [
      {
        "x": 4,
        "y": 0,
        "z": 2000
      },
      {
        "x": 3,
        "y": 0,
        "z": 5000
      },
      {
        "x": 5,
        "y": 5012001,
        "z": 3
      }
    ],
    "sweep_monster_once": [
      {
        "x": 500,
        "y": 3,
        "z": 5
      }
    ]
  },
  {
    "id": 74,
    "level_id": 10074,
    "block_id": 8,
    "cost": [
      {
        "x": 1,
        "y": 0,
        "z": 5
      }
    ],
    "money": 4200,
    "exp": 1680,
    "patrol_unit": 10074,
    "patrol_once": [
      {
        "x": 5,
        "y": 1020000,
        "z": 14
      },
      {
        "x": 5,
        "y": 5012001,
        "z": 5
      },
      {
        "x": 5,
        "y": 1030002,
        "z": 70
      }
    ],
    "sweep_once": [
      {
        "x": 4,
        "y": 0,
        "z": 2000
      },
      {
        "x": 3,
        "y": 0,
        "z": 5000
      },
      {
        "x": 5,
        "y": 5012001,
        "z": 3
      }
    ],
    "sweep_monster_once": [
      {
        "x": 500,
        "y": 3,
        "z": 5
      }
    ]
  },
  {
    "id": 75,
    "level_id": 10075,
    "block_id": 8,
    "cost": [
      {
        "x": 1,
        "y": 0,
        "z": 5
      }
    ],
    "money": 4250,
    "exp": 1700,
    "patrol_unit": 10075,
    "patrol_once": [
      {
        "x": 5,
        "y": 1020000,
        "z": 14
      },
      {
        "x": 5,
        "y": 5012001,
        "z": 5
      },
      {
        "x": 5,
        "y": 1030002,
        "z": 71
      }
    ],
    "sweep_once": [
      {
        "x": 4,
        "y": 0,
        "z": 2000
      },
      {
        "x": 3,
        "y": 0,
        "z": 5000
      },
      {
        "x": 5,
        "y": 5012001,
        "z": 3
      }
    ],
    "sweep_monster_once": [
      {
        "x": 500,
        "y": 3,
        "z": 5
      }
    ]
  },
  {
    "id": 76,
    "level_id": 10076,
    "block_id": 8,
    "cost": [
      {
        "x": 1,
        "y": 0,
        "z": 5
      }
    ],
    "money": 4300,
    "exp": 1720,
    "patrol_unit": 10076,
    "patrol_once": [
      {
        "x": 5,
        "y": 1020000,
        "z": 14
      },
      {
        "x": 5,
        "y": 5012001,
        "z": 5
      },
      {
        "x": 5,
        "y": 1030002,
        "z": 71
      }
    ],
    "sweep_once": [
      {
        "x": 4,
        "y": 0,
        "z": 2000
      },
      {
        "x": 3,
        "y": 0,
        "z": 5000
      },
      {
        "x": 5,
        "y": 5012001,
        "z": 3
      }
    ],
    "sweep_monster_once": [
      {
        "x": 500,
        "y": 3,
        "z": 5
      }
    ]
  },
  {
    "id": 77,
    "level_id": 10077,
    "block_id": 8,
    "cost": [
      {
        "x": 1,
        "y": 0,
        "z": 5
      }
    ],
    "money": 4350,
    "exp": 1740,
    "patrol_unit": 10077,
    "patrol_once": [
      {
        "x": 5,
        "y": 1020000,
        "z": 14
      },
      {
        "x": 5,
        "y": 5012001,
        "z": 5
      },
      {
        "x": 5,
        "y": 1030002,
        "z": 71
      }
    ],
    "sweep_once": [
      {
        "x": 4,
        "y": 0,
        "z": 2000
      },
      {
        "x": 3,
        "y": 0,
        "z": 5000
      },
      {
        "x": 5,
        "y": 5012001,
        "z": 3
      }
    ],
    "sweep_monster_once": [
      {
        "x": 500,
        "y": 3,
        "z": 5
      }
    ]
  },
  {
    "id": 78,
    "level_id": 10078,
    "block_id": 8,
    "cost": [
      {
        "x": 1,
        "y": 0,
        "z": 5
      }
    ],
    "money": 4400,
    "exp": 1760,
    "patrol_unit": 10078,
    "patrol_once": [
      {
        "x": 5,
        "y": 1020000,
        "z": 14
      },
      {
        "x": 5,
        "y": 5012001,
        "z": 5
      },
      {
        "x": 5,
        "y": 1030002,
        "z": 71
      }
    ],
    "sweep_once": [
      {
        "x": 4,
        "y": 0,
        "z": 2000
      },
      {
        "x": 3,
        "y": 0,
        "z": 5000
      },
      {
        "x": 5,
        "y": 5012001,
        "z": 3
      }
    ],
    "sweep_monster_once": [
      {
        "x": 500,
        "y": 3,
        "z": 5
      }
    ]
  },
  {
    "id": 79,
    "level_id": 10079,
    "block_id": 8,
    "cost": [
      {
        "x": 1,
        "y": 0,
        "z": 5
      }
    ],
    "money": 4450,
    "exp": 1780,
    "patrol_unit": 10079,
    "patrol_once": [
      {
        "x": 5,
        "y": 1020000,
        "z": 14
      },
      {
        "x": 5,
        "y": 5012001,
        "z": 5
      },
      {
        "x": 5,
        "y": 1030002,
        "z": 71
      }
    ],
    "sweep_once": [
      {
        "x": 4,
        "y": 0,
        "z": 2000
      },
      {
        "x": 3,
        "y": 0,
        "z": 5000
      },
      {
        "x": 5,
        "y": 5012001,
        "z": 3
      }
    ],
    "sweep_monster_once": [
      {
        "x": 500,
        "y": 3,
        "z": 5
      }
    ]
  },
  {
    "id": 80,
    "level_id": 10080,
    "block_id": 8,
    "cost": [
      {
        "x": 1,
        "y": 0,
        "z": 5
      }
    ],
    "money": 4500,
    "exp": 1800,
    "patrol_unit": 10080,
    "patrol_once": [
      {
        "x": 5,
        "y": 1020000,
        "z": 14
      },
      {
        "x": 5,
        "y": 5012001,
        "z": 5
      },
      {
        "x": 5,
        "y": 1030002,
        "z": 72
      }
    ],
    "sweep_once": [
      {
        "x": 4,
        "y": 0,
        "z": 2000
      },
      {
        "x": 3,
        "y": 0,
        "z": 5000
      },
      {
        "x": 5,
        "y": 5012001,
        "z": 3
      }
    ],
    "sweep_monster_once": [
      {
        "x": 500,
        "y": 3,
        "z": 5
      }
    ]
  },
  {
    "id": 81,
    "level_id": 10081,
    "block_id": 9,
    "cost": [
      {
        "x": 1,
        "y": 0,
        "z": 5
      }
    ],
    "money": 4550,
    "exp": 1820,
    "patrol_unit": 10081,
    "patrol_once": [
      {
        "x": 5,
        "y": 1020000,
        "z": 15
      },
      {
        "x": 5,
        "y": 5012001,
        "z": 5
      },
      {
        "x": 5,
        "y": 1030002,
        "z": 72
      }
    ],
    "sweep_once": [
      {
        "x": 4,
        "y": 0,
        "z": 2000
      },
      {
        "x": 3,
        "y": 0,
        "z": 5000
      },
      {
        "x": 5,
        "y": 5012001,
        "z": 3
      }
    ],
    "sweep_monster_once": [
      {
        "x": 500,
        "y": 3,
        "z": 5
      }
    ]
  },
  {
    "id": 82,
    "level_id": 10082,
    "block_id": 9,
    "cost": [
      {
        "x": 1,
        "y": 0,
        "z": 5
      }
    ],
    "money": 4600,
    "exp": 1840,
    "patrol_unit": 10082,
    "patrol_once": [
      {
        "x": 5,
        "y": 1020000,
        "z": 15
      },
      {
        "x": 5,
        "y": 5012001,
        "z": 5
      },
      {
        "x": 5,
        "y": 1030002,
        "z": 72
      }
    ],
    "sweep_once": [
      {
        "x": 4,
        "y": 0,
        "z": 2000
      },
      {
        "x": 3,
        "y": 0,
        "z": 5000
      },
      {
        "x": 5,
        "y": 5012001,
        "z": 3
      }
    ],
    "sweep_monster_once": [
      {
        "x": 500,
        "y": 3,
        "z": 5
      }
    ]
  },
  {
    "id": 83,
    "level_id": 10083,
    "block_id": 9,
    "cost": [
      {
        "x": 1,
        "y": 0,
        "z": 5
      }
    ],
    "money": 4650,
    "exp": 1860,
    "patrol_unit": 10083,
    "patrol_once": [
      {
        "x": 5,
        "y": 1020000,
        "z": 15
      },
      {
        "x": 5,
        "y": 5012001,
        "z": 5
      },
      {
        "x": 5,
        "y": 1030002,
        "z": 72
      }
    ],
    "sweep_once": [
      {
        "x": 4,
        "y": 0,
        "z": 2000
      },
      {
        "x": 3,
        "y": 0,
        "z": 5000
      },
      {
        "x": 5,
        "y": 5012001,
        "z": 3
      }
    ],
    "sweep_monster_once": [
      {
        "x": 500,
        "y": 3,
        "z": 5
      }
    ]
  },
  {
    "id": 84,
    "level_id": 10084,
    "block_id": 9,
    "cost": [
      {
        "x": 1,
        "y": 0,
        "z": 5
      }
    ],
    "money": 4700,
    "exp": 1880,
    "patrol_unit": 10084,
    "patrol_once": [
      {
        "x": 5,
        "y": 1020000,
        "z": 15
      },
      {
        "x": 5,
        "y": 5012001,
        "z": 5
      },
      {
        "x": 5,
        "y": 1030002,
        "z": 72
      }
    ],
    "sweep_once": [
      {
        "x": 4,
        "y": 0,
        "z": 2000
      },
      {
        "x": 3,
        "y": 0,
        "z": 5000
      },
      {
        "x": 5,
        "y": 5012001,
        "z": 3
      }
    ],
    "sweep_monster_once": [
      {
        "x": 500,
        "y": 3,
        "z": 5
      }
    ]
  },
  {
    "id": 85,
    "level_id": 10085,
    "block_id": 9,
    "cost": [
      {
        "x": 1,
        "y": 0,
        "z": 5
      }
    ],
    "money": 4750,
    "exp": 1900,
    "patrol_unit": 10085,
    "patrol_once": [
      {
        "x": 5,
        "y": 1020000,
        "z": 15
      },
      {
        "x": 5,
        "y": 5012001,
        "z": 5
      },
      {
        "x": 5,
        "y": 1030002,
        "z": 73
      }
    ],
    "sweep_once": [
      {
        "x": 4,
        "y": 0,
        "z": 2000
      },
      {
        "x": 3,
        "y": 0,
        "z": 5000
      },
      {
        "x": 5,
        "y": 5012001,
        "z": 3
      }
    ],
    "sweep_monster_once": [
      {
        "x": 500,
        "y": 3,
        "z": 5
      }
    ]
  },
  {
    "id": 86,
    "level_id": 10086,
    "block_id": 9,
    "cost": [
      {
        "x": 1,
        "y": 0,
        "z": 5
      }
    ],
    "money": 4800,
    "exp": 1920,
    "patrol_unit": 10086,
    "patrol_once": [
      {
        "x": 5,
        "y": 1020000,
        "z": 15
      },
      {
        "x": 5,
        "y": 5012001,
        "z": 5
      },
      {
        "x": 5,
        "y": 1030002,
        "z": 73
      }
    ],
    "sweep_once": [
      {
        "x": 4,
        "y": 0,
        "z": 2000
      },
      {
        "x": 3,
        "y": 0,
        "z": 5000
      },
      {
        "x": 5,
        "y": 5012001,
        "z": 3
      }
    ],
    "sweep_monster_once": [
      {
        "x": 500,
        "y": 3,
        "z": 5
      }
    ]
  },
  {
    "id": 87,
    "level_id": 10087,
    "block_id": 9,
    "cost": [
      {
        "x": 1,
        "y": 0,
        "z": 5
      }
    ],
    "money": 4850,
    "exp": 1940,
    "patrol_unit": 10087,
    "patrol_once": [
      {
        "x": 5,
        "y": 1020000,
        "z": 15
      },
      {
        "x": 5,
        "y": 5012001,
        "z": 5
      },
      {
        "x": 5,
        "y": 1030002,
        "z": 73
      }
    ],
    "sweep_once": [
      {
        "x": 4,
        "y": 0,
        "z": 2000
      },
      {
        "x": 3,
        "y": 0,
        "z": 5000
      },
      {
        "x": 5,
        "y": 5012001,
        "z": 3
      }
    ],
    "sweep_monster_once": [
      {
        "x": 500,
        "y": 3,
        "z": 5
      }
    ]
  },
  {
    "id": 88,
    "level_id": 10088,
    "block_id": 9,
    "cost": [
      {
        "x": 1,
        "y": 0,
        "z": 5
      }
    ],
    "money": 4900,
    "exp": 1960,
    "patrol_unit": 10088,
    "patrol_once": [
      {
        "x": 5,
        "y": 1020000,
        "z": 15
      },
      {
        "x": 5,
        "y": 5012001,
        "z": 5
      },
      {
        "x": 5,
        "y": 1030002,
        "z": 73
      }
    ],
    "sweep_once": [
      {
        "x": 4,
        "y": 0,
        "z": 2000
      },
      {
        "x": 3,
        "y": 0,
        "z": 5000
      },
      {
        "x": 5,
        "y": 5012001,
        "z": 3
      }
    ],
    "sweep_monster_once": [
      {
        "x": 500,
        "y": 3,
        "z": 5
      }
    ]
  },
  {
    "id": 89,
    "level_id": 10089,
    "block_id": 9,
    "cost": [
      {
        "x": 1,
        "y": 0,
        "z": 5
      }
    ],
    "money": 4950,
    "exp": 1980,
    "patrol_unit": 10089,
    "patrol_once": [
      {
        "x": 5,
        "y": 1020000,
        "z": 15
      },
      {
        "x": 5,
        "y": 5012001,
        "z": 5
      },
      {
        "x": 5,
        "y": 1030002,
        "z": 73
      }
    ],
    "sweep_once": [
      {
        "x": 4,
        "y": 0,
        "z": 2000
      },
      {
        "x": 3,
        "y": 0,
        "z": 5000
      },
      {
        "x": 5,
        "y": 5012001,
        "z": 3
      }
    ],
    "sweep_monster_once": [
      {
        "x": 500,
        "y": 3,
        "z": 5
      }
    ]
  },
  {
    "id": 90,
    "level_id": 10090,
    "block_id": 9,
    "cost": [
      {
        "x": 1,
        "y": 0,
        "z": 5
      }
    ],
    "money": 5000,
    "exp": 2000,
    "patrol_unit": 10090,
    "patrol_once": [
      {
        "x": 5,
        "y": 1020000,
        "z": 15
      },
      {
        "x": 5,
        "y": 5012001,
        "z": 5
      },
      {
        "x": 5,
        "y": 1030002,
        "z": 74
      }
    ],
    "sweep_once": [
      {
        "x": 4,
        "y": 0,
        "z": 2000
      },
      {
        "x": 3,
        "y": 0,
        "z": 5000
      },
      {
        "x": 5,
        "y": 5012001,
        "z": 3
      }
    ],
    "sweep_monster_once": [
      {
        "x": 500,
        "y": 3,
        "z": 5
      }
    ]
  },
  {
    "id": 91,
    "level_id": 10091,
    "block_id": 10,
    "cost": [
      {
        "x": 1,
        "y": 0,
        "z": 5
      }
    ],
    "money": 5075,
    "exp": 2050,
    "patrol_unit": 10091,
    "patrol_once": [
      {
        "x": 5,
        "y": 1020000,
        "z": 15
      },
      {
        "x": 5,
        "y": 5012001,
        "z": 5
      },
      {
        "x": 5,
        "y": 1030002,
        "z": 74
      }
    ],
    "sweep_once": [
      {
        "x": 4,
        "y": 0,
        "z": 2000
      },
      {
        "x": 3,
        "y": 0,
        "z": 5000
      },
      {
        "x": 5,
        "y": 5012001,
        "z": 3
      }
    ],
    "sweep_monster_once": [
      {
        "x": 500,
        "y": 3,
        "z": 5
      }
    ]
  },
  {
    "id": 92,
    "level_id": 10092,
    "block_id": 10,
    "cost": [
      {
        "x": 1,
        "y": 0,
        "z": 5
      }
    ],
    "money": 5150,
    "exp": 2100,
    "patrol_unit": 10092,
    "patrol_once": [
      {
        "x": 5,
        "y": 1020000,
        "z": 15
      },
      {
        "x": 5,
        "y": 5012001,
        "z": 5
      },
      {
        "x": 5,
        "y": 1030002,
        "z": 74
      }
    ],
    "sweep_once": [
      {
        "x": 4,
        "y": 0,
        "z": 2000
      },
      {
        "x": 3,
        "y": 0,
        "z": 5000
      },
      {
        "x": 5,
        "y": 5012001,
        "z": 3
      }
    ],
    "sweep_monster_once": [
      {
        "x": 500,
        "y": 3,
        "z": 5
      }
    ]
  },
  {
    "id": 93,
    "level_id": 10093,
    "block_id": 10,
    "cost": [
      {
        "x": 1,
        "y": 0,
        "z": 5
      }
    ],
    "money": 5225,
    "exp": 2150,
    "patrol_unit": 10093,
    "patrol_once": [
      {
        "x": 5,
        "y": 1020000,
        "z": 15
      },
      {
        "x": 5,
        "y": 5012001,
        "z": 5
      },
      {
        "x": 5,
        "y": 1030002,
        "z": 74
      }
    ],
    "sweep_once": [
      {
        "x": 4,
        "y": 0,
        "z": 2000
      },
      {
        "x": 3,
        "y": 0,
        "z": 5000
      },
      {
        "x": 5,
        "y": 5012001,
        "z": 3
      }
    ],
    "sweep_monster_once": [
      {
        "x": 500,
        "y": 3,
        "z": 5
      }
    ]
  },
  {
    "id": 94,
    "level_id": 10094,
    "block_id": 10,
    "cost": [
      {
        "x": 1,
        "y": 0,
        "z": 5
      }
    ],
    "money": 5300,
    "exp": 2200,
    "patrol_unit": 10094,
    "patrol_once": [
      {
        "x": 5,
        "y": 1020000,
        "z": 15
      },
      {
        "x": 5,
        "y": 5012001,
        "z": 5
      },
      {
        "x": 5,
        "y": 1030002,
        "z": 74
      }
    ],
    "sweep_once": [
      {
        "x": 4,
        "y": 0,
        "z": 2000
      },
      {
        "x": 3,
        "y": 0,
        "z": 5000
      },
      {
        "x": 5,
        "y": 5012001,
        "z": 3
      }
    ],
    "sweep_monster_once": [
      {
        "x": 500,
        "y": 3,
        "z": 5
      }
    ]
  },
  {
    "id": 95,
    "level_id": 10095,
    "block_id": 10,
    "cost": [
      {
        "x": 1,
        "y": 0,
        "z": 5
      }
    ],
    "money": 5375,
    "exp": 2250,
    "patrol_unit": 10095,
    "patrol_once": [
      {
        "x": 5,
        "y": 1020000,
        "z": 15
      },
      {
        "x": 5,
        "y": 5012001,
        "z": 5
      },
      {
        "x": 5,
        "y": 1030002,
        "z": 75
      }
    ],
    "sweep_once": [
      {
        "x": 4,
        "y": 0,
        "z": 2000
      },
      {
        "x": 3,
        "y": 0,
        "z": 5000
      },
      {
        "x": 5,
        "y": 5012001,
        "z": 3
      }
    ],
    "sweep_monster_once": [
      {
        "x": 500,
        "y": 3,
        "z": 5
      }
    ]
  },
  {
    "id": 96,
    "level_id": 10096,
    "block_id": 10,
    "cost": [
      {
        "x": 1,
        "y": 0,
        "z": 5
      }
    ],
    "money": 5450,
    "exp": 2300,
    "patrol_unit": 10096,
    "patrol_once": [
      {
        "x": 5,
        "y": 1020000,
        "z": 15
      },
      {
        "x": 5,
        "y": 5012001,
        "z": 5
      },
      {
        "x": 5,
        "y": 1030002,
        "z": 75
      }
    ],
    "sweep_once": [
      {
        "x": 4,
        "y": 0,
        "z": 2000
      },
      {
        "x": 3,
        "y": 0,
        "z": 5000
      },
      {
        "x": 5,
        "y": 5012001,
        "z": 3
      }
    ],
    "sweep_monster_once": [
      {
        "x": 500,
        "y": 3,
        "z": 5
      }
    ]
  },
  {
    "id": 97,
    "level_id": 10097,
    "block_id": 10,
    "cost": [
      {
        "x": 1,
        "y": 0,
        "z": 5
      }
    ],
    "money": 5525,
    "exp": 2350,
    "patrol_unit": 10097,
    "patrol_once": [
      {
        "x": 5,
        "y": 1020000,
        "z": 15
      },
      {
        "x": 5,
        "y": 5012001,
        "z": 5
      },
      {
        "x": 5,
        "y": 1030002,
        "z": 75
      }
    ],
    "sweep_once": [
      {
        "x": 4,
        "y": 0,
        "z": 2000
      },
      {
        "x": 3,
        "y": 0,
        "z": 5000
      },
      {
        "x": 5,
        "y": 5012001,
        "z": 3
      }
    ],
    "sweep_monster_once": [
      {
        "x": 500,
        "y": 3,
        "z": 5
      }
    ]
  },
  {
    "id": 98,
    "level_id": 10098,
    "block_id": 10,
    "cost": [
      {
        "x": 1,
        "y": 0,
        "z": 5
      }
    ],
    "money": 5600,
    "exp": 2400,
    "patrol_unit": 10098,
    "patrol_once": [
      {
        "x": 5,
        "y": 1020000,
        "z": 15
      },
      {
        "x": 5,
        "y": 5012001,
        "z": 5
      },
      {
        "x": 5,
        "y": 1030002,
        "z": 75
      }
    ],
    "sweep_once": [
      {
        "x": 4,
        "y": 0,
        "z": 2000
      },
      {
        "x": 3,
        "y": 0,
        "z": 5000
      },
      {
        "x": 5,
        "y": 5012001,
        "z": 3
      }
    ],
    "sweep_monster_once": [
      {
        "x": 500,
        "y": 3,
        "z": 5
      }
    ]
  },
  {
    "id": 99,
    "level_id": 10099,
    "block_id": 10,
    "cost": [
      {
        "x": 1,
        "y": 0,
        "z": 5
      }
    ],
    "money": 5675,
    "exp": 2450,
    "patrol_unit": 10099,
    "patrol_once": [
      {
        "x": 5,
        "y": 1020000,
        "z": 15
      },
      {
        "x": 5,
        "y": 5012001,
        "z": 5
      },
      {
        "x": 5,
        "y": 1030002,
        "z": 75
      }
    ],
    "sweep_once": [
      {
        "x": 4,
        "y": 0,
        "z": 2000
      },
      {
        "x": 3,
        "y": 0,
        "z": 5000
      },
      {
        "x": 5,
        "y": 5012001,
        "z": 3
      }
    ],
    "sweep_monster_once": [
      {
        "x": 500,
        "y": 3,
        "z": 5
      }
    ]
  }
]