[
  {
    "id": 1,
    "score": 200,
    "reward": [
      {
        "x": 2,
        "y": 0,
        "z": 10
      }
    ]
  },
  {
    "id": 2,
    "score": 400,
    "reward": [
      {
        "x": 2,
        "y": 0,
        "z": 10
      }
    ]
  },
  {
    "id": 3,
    "score": 600,
    "reward": [
      {
        "x": 2,
        "y": 0,
        "z": 10
      }
    ]
  },
  {
    "id": 4,
    "score": 800,
    "reward": [
      {
        "x": 2,
        "y": 0,
        "z": 10
      }
    ]
  },
  {
    "id": 5,
    "score": 1000,
    "reward": [
      {
        "x": 2,
        "y": 0,
        "z": 10
      }
    ]
  },
  {
    "id": 6,
    "score": 1200,
    "reward": [
      {
        "x": 2,
        "y": 0,
        "z": 10
      }
    ]
  },
  {
    "id": 7,
    "score": 1400,
    "reward": [
      {
        "x": 2,
        "y": 0,
        "z": 10
      }
    ]
  },
  {
    "id": 8,
    "score": 1600,
    "reward": [
      {
        "x": 2,
        "y": 0,
        "z": 10
      }
    ]
  },
  {
    "id": 9,
    "score": 1800,
    "reward": [
      {
        "x": 2,
        "y": 0,
        "z": 10
      }
    ]
  },
  {
    "id": 10,
    "score": 2000,
    "reward": [
      {
        "x": 2,
        "y": 0,
        "z": 20
      }
    ]
  },
  {
    "id": 11,
    "score": 2200,
    "reward": [
      {
        "x": 2,
        "y": 0,
        "z": 20
      }
    ]
  },
  {
    "id": 12,
    "score": 2400,
    "reward": [
      {
        "x": 2,
        "y": 0,
        "z": 20
      }
    ]
  },
  {
    "id": 13,
    "score": 2600,
    "reward": [
      {
        "x": 2,
        "y": 0,
        "z": 20
      }
    ]
  },
  {
    "id": 14,
    "score": 2800,
    "reward": [
      {
        "x": 2,
        "y": 0,
        "z": 20
      }
    ]
  },
  {
    "id": 15,
    "score": 3000,
    "reward": [
      {
        "x": 2,
        "y": 0,
        "z": 20
      }
    ]
  },
  {
    "id": 16,
    "score": 3200,
    "reward": [
      {
        "x": 2,
        "y": 0,
        "z": 20
      }
    ]
  },
  {
    "id": 17,
    "score": 3400,
    "reward": [
      {
        "x": 2,
        "y": 0,
        "z": 20
      }
    ]
  },
  {
    "id": 18,
    "score": 3600,
    "reward": [
      {
        "x": 2,
        "y": 0,
        "z": 20
      }
    ]
  },
  {
    "id": 19,
    "score": 3800,
    "reward": [
      {
        "x": 2,
        "y": 0,
        "z": 20
      }
    ]
  },
  {
    "id": 20,
    "score": 4000,
    "reward": [
      {
        "x": 2,
        "y": 0,
        "z": 30
      }
    ]
  },
  {
    "id": 21,
    "score": 4200,
    "reward": [
      {
        "x": 2,
        "y": 0,
        "z": 30
      }
    ]
  },
  {
    "id": 22,
    "score": 4400,
    "reward": [
      {
        "x": 2,
        "y": 0,
        "z": 30
      }
    ]
  },
  {
    "id": 23,
    "score": 4600,
    "reward": [
      {
        "x": 2,
        "y": 0,
        "z": 30
      }
    ]
  },
  {
    "id": 24,
    "score": 4800,
    "reward": [
      {
        "x": 2,
        "y": 0,
        "z": 30
      }
    ]
  },
  {
    "id": 25,
    "score": 5000,
    "reward": [
      {
        "x": 2,
        "y": 0,
        "z": 30
      }
    ]
  },
  {
    "id": 26,
    "score": 5200,
    "reward": [
      {
        "x": 2,
        "y": 0,
        "z": 30
      }
    ]
  },
  {
    "id": 27,
    "score": 5400,
    "reward": [
      {
        "x": 2,
        "y": 0,
        "z": 30
      }
    ]
  },
  {
    "id": 28,
    "score": 5600,
    "reward": [
      {
        "x": 2,
        "y": 0,
        "z": 30
      }
    ]
  },
  {
    "id": 29,
    "score": 5800,
    "reward": [
      {
        "x": 2,
        "y": 0,
        "z": 30
      }
    ]
  },
  {
    "id": 30,
    "score": 6000,
    "reward": [
      {
        "x": 2,
        "y": 0,
        "z": 40
      }
    ]
  },
  {
    "id": 31,
    "score": 6200,
    "reward": [
      {
        "x": 2,
        "y": 0,
        "z": 40
      }
    ]
  },
  {
    "id": 32,
    "score": 6400,
    "reward": [
      {
        "x": 2,
        "y": 0,
        "z": 40
      }
    ]
  },
  {
    "id": 33,
    "score": 6600,
    "reward": [
      {
        "x": 2,
        "y": 0,
        "z": 40
      }
    ]
  },
  {
    "id": 34,
    "score": 6800,
    "reward": [
      {
        "x": 2,
        "y": 0,
        "z": 40
      }
    ]
  },
  {
    "id": 35,
    "score": 7000,
    "reward": [
      {
        "x": 2,
        "y": 0,
        "z": 40
      }
    ]
  },
  {
    "id": 36,
    "score": 7200,
    "reward": [
      {
        "x": 2,
        "y": 0,
        "z": 40
      }
    ]
  },
  {
    "id": 37,
    "score": 7400,
    "reward": [
      {
        "x": 2,
        "y": 0,
        "z": 40
      }
    ]
  },
  {
    "id": 38,
    "score": 7600,
    "reward": [
      {
        "x": 2,
        "y": 0,
        "z": 40
      }
    ]
  },
  {
    "id": 39,
    "score": 7800,
    "reward": [
      {
        "x": 2,
        "y": 0,
        "z": 40
      }
    ]
  },
  {
    "id": 40,
    "score": 8000,
    "reward": [
      {
        "x": 2,
        "y": 0,
        "z": 50
      }
    ]
  },
  {
    "id": 41,
    "score": 8200,
    "reward": [
      {
        "x": 2,
        "y": 0,
        "z": 50
      }
    ]
  },
  {
    "id": 42,
    "score": 8400,
    "reward": [
      {
        "x": 2,
        "y": 0,
        "z": 50
      }
    ]
  },
  {
    "id": 43,
    "score": 8600,
    "reward": [
      {
        "x": 2,
        "y": 0,
        "z": 50
      }
    ]
  },
  {
    "id": 44,
    "score": 8800,
    "reward": [
      {
        "x": 2,
        "y": 0,
        "z": 50
      }
    ]
  },
  {
    "id": 45,
    "score": 9000,
    "reward": [
      {
        "x": 2,
        "y": 0,
        "z": 50
      }
    ]
  },
  {
    "id": 46,
    "score": 9200,
    "reward": [
      {
        "x": 2,
        "y": 0,
        "z": 50
      }
    ]
  },
  {
    "id": 47,
    "score": 9400,
    "reward": [
      {
        "x": 2,
        "y": 0,
        "z": 50
      }
    ]
  },
  {
    "id": 48,
    "score": 9600,
    "reward": [
      {
        "x": 2,
        "y": 0,
        "z": 50
      }
    ]
  },
  {
    "id": 49,
    "score": 9800,
    "reward": [
      {
        "x": 2,
        "y": 0,
        "z": 50
      }
    ]
  },
  {
    "id": 50,
    "score": 10000,
    "reward": [
      {
        "x": 2,
        "y": 0,
        "z": 60
      }
    ]
  },
  {
    "id": 51,
    "score": 10200,
    "reward": [
      {
        "x": 2,
        "y": 0,
        "z": 60
      }
    ]
  },
  {
    "id": 52,
    "score": 10400,
    "reward": [
      {
        "x": 2,
        "y": 0,
        "z": 60
      }
    ]
  },
  {
    "id": 53,
    "score": 10600,
    "reward": [
      {
        "x": 2,
        "y": 0,
        "z": 60
      }
    ]
  },
  {
    "id": 54,
    "score": 10800,
    "reward": [
      {
        "x": 2,
        "y": 0,
        "z": 60
      }
    ]
  },
  {
    "id": 55,
    "score": 11000,
    "reward": [
      {
        "x": 2,
        "y": 0,
        "z": 60
      }
    ]
  },
  {
    "id": 56,
    "score": 11200,
    "reward": [
      {
        "x": 2,
        "y": 0,
        "z": 60
      }
    ]
  },
  {
    "id": 57,
    "score": 11400,
    "reward": [
      {
        "x": 2,
        "y": 0,
        "z": 60
      }
    ]
  },
  {
    "id": 58,
    "score": 11600,
    "reward": [
      {
        "x": 2,
        "y": 0,
        "z": 60
      }
    ]
  },
  {
    "id": 59,
    "score": 11800,
    "reward": [
      {
        "x": 2,
        "y": 0,
        "z": 60
      }
    ]
  },
  {
    "id": 60,
    "score": 12000,
    "reward": [
      {
        "x": 2,
        "y": 0,
        "z": 70
      }
    ]
  }
]